ghworkspace/__init__.py
ghworkspace/__version__.py
ghworkspace-0.0.3.dist-info/WHEEL
ghworkspace-0.0.3.dist-info/METADATA
ghworkspace-0.0.3.dist-info/RECORD
