Metadata-Version: 2.1
Name: ghworkspace
Version: 0.0.3
Summary: 
Author: m3y
Author-email: ma3ya.ozw+pypi@gmail.com
Requires-Python: >=3.8,<4.0
Classifier: Programming Language :: Python :: 3
Classifier: Programming Language :: Python :: 3.8
Classifier: Programming Language :: Python :: 3.9
Requires-Dist: PyGithub (>=1.53,<2.0)
